setup.py
drf_mongoengine_cache/__init__.py
drf_mongoengine_cache/cache.py
drf_mongoengine_cache/exceptions.py
drf_mongoengine_cache/registry.py
drf_mongoengine_cache/serializers.py
drf_mongoengine_cache/settings.py
drf_mongoengine_cache/signals.py
drf_mongoengine_cache/utils.py
drf_mongoengine_cache.egg-info/PKG-INFO
drf_mongoengine_cache.egg-info/SOURCES.txt
drf_mongoengine_cache.egg-info/dependency_links.txt
drf_mongoengine_cache.egg-info/namespace_packages.txt
drf_mongoengine_cache.egg-info/top_level.txt