Metadata-Version: 1.1
Name: drf-mongoengine-cache
Version: 0.6
Summary: Easy to use cache framework for django-rest-framwork with MongoEngine models
Home-page: https://github.com/albertomr86/drf-mongoengine-cache
Author: Alberto Menendez Romero
Author-email: albertomr86@gmail.com
License: GPLv3
Download-URL: https://github.com/albertomr86/drf-mongoengine-cache/tarball/master
Keywords: drf_mongoengine_cache
Platform: UNKNOWN
Classifier: Development Status :: 3 - Alpha
Classifier: Framework :: Django
Classifier: Topic :: Utilities
Classifier: Environment :: Plugins
Classifier: License :: OSI Approved :: GNU General Public License v3 (GPLv3)
Classifier: Operating System :: OS Independent
Classifier: Intended Audience :: Developers
